suffix_expression/__init__.py
suffix_expression/__init__.pyi
suffix_expression-2024.8.23.dist-info/LICENSE.txt
suffix_expression-2024.8.23.dist-info/METADATA
suffix_expression-2024.8.23.dist-info/WHEEL
suffix_expression-2024.8.23.dist-info/top_level.txt
suffix_expression-2024.8.23.dist-info/RECORD
