Metadata-Version: 2.1
Name: suffix_expression
Version: 2024.8.23
Summary: 后缀表达式处理库
Home-page: https://github.com/longliangzhe/suffix_expression
Author: Lighting Long
Author-email: 17818883308@139.com
Classifier: Programming Language :: Python :: 3
Classifier: Programming Language :: Python :: 3.13
Classifier: Programming Language :: Python :: 3.12
Classifier: Programming Language :: Python :: 3.11
Classifier: Programming Language :: Python :: 3.10
Classifier: Programming Language :: Python :: 3.9
Classifier: Programming Language :: Python :: 3.8
Classifier: License :: OSI Approved :: MIT License
Classifier: Operating System :: OS Independent
Requires-Python: >=3.8
License-File: LICENSE.txt
